{
  "slug": "roslyn",
  "drafts": 264,
  "elapsed": 94.9,
  "scanned": 500,
  "schedule_desc": "~daily",
  "reports": {
    "top15": {
      "count": 230,
      "title": "Most Actionable PRs",
      "file": "actionable.html"
    },
    "stale-close": {
      "count": 177,
      "title": "Consider Closing",
      "file": "consider-closing.html"
    },
    "quick-wins": {
      "count": 2,
      "title": "Quick Wins: Ready to Merge",
      "file": "quick-wins.html"
    },
    "community": {
      "count": 27,
      "title": "Community PRs Awaiting Review",
      "file": "community.html"
    }
  },
  "updated": "2026-04-02T18:00:53.6616556Z",
  "repo": "dotnet/roslyn",
  "analyzed": 230,
  "bots": 6
}
