{
  "reports": {
    "top15": {
      "title": "Most Actionable PRs",
      "count": 223,
      "file": "actionable.html"
    },
    "quick-wins": {
      "title": "Quick Wins: Ready to Merge",
      "count": 0,
      "file": "quick-wins.html"
    },
    "stale-close": {
      "title": "Consider Closing",
      "count": 169,
      "file": "consider-closing.html"
    },
    "community": {
      "title": "Community PRs Awaiting Review",
      "count": 24,
      "file": "community.html"
    }
  },
  "repo": "dotnet/roslyn",
  "scanned": 500,
  "schedule_desc": "~daily",
  "drafts": 271,
  "bots": 6,
  "elapsed": 88.2,
  "updated": "2026-03-27T07:44:32.7622176Z",
  "analyzed": 223,
  "slug": "roslyn"
}
