{
  "updated": "2026-03-03T20:39:08.8184150Z",
  "reports": {
    "top15": {
      "title": "Most Actionable PRs",
      "count": 265,
      "file": "actionable.html"
    },
    "community": {
      "title": "Community PRs Awaiting Review",
      "count": 32,
      "file": "community.html"
    },
    "quick-wins": {
      "title": "Quick Wins: Ready to Merge",
      "count": 0,
      "file": "quick-wins.html"
    },
    "stale-close": {
      "title": "Consider Closing",
      "count": 81,
      "file": "consider-closing.html"
    }
  },
  "drafts": 125,
  "elapsed": 107.3,
  "slug": "runtime",
  "bots": 32,
  "repo": "dotnet/runtime",
  "analyzed": 265,
  "scanned": 422
}
