{
  "slug": "extensions",
  "updated": "2026-03-14T02:46:52.8870131Z",
  "scanned": 24,
  "analyzed": 16,
  "drafts": 6,
  "repo": "dotnet/extensions",
  "bots": 2,
  "reports": {
    "top15": {
      "title": "Most Actionable PRs",
      "count": 16,
      "file": "actionable.html"
    },
    "quick-wins": {
      "title": "Quick Wins: Ready to Merge",
      "count": 0,
      "file": "quick-wins.html"
    },
    "stale-close": {
      "title": "Consider Closing",
      "count": 6,
      "file": "consider-closing.html"
    },
    "community": {
      "title": "Community PRs Awaiting Review",
      "count": 0,
      "file": "community.html"
    }
  },
  "elapsed": 4.1
}
