{
  "reports": {
    "community": {
      "file": "community.html",
      "title": "Community PRs Awaiting Review",
      "count": 0
    },
    "top15": {
      "file": "actionable.html",
      "title": "Most Actionable PRs",
      "count": 14
    },
    "stale-close": {
      "file": "consider-closing.html",
      "title": "Consider Closing",
      "count": 6
    },
    "quick-wins": {
      "file": "quick-wins.html",
      "title": "Quick Wins: Ready to Merge",
      "count": 0
    }
  },
  "slug": "extensions",
  "bots": 1,
  "updated": "2026-03-25T07:08:52.9861662Z",
  "scanned": 22,
  "elapsed": 6.8,
  "analyzed": 14,
  "repo": "dotnet/extensions",
  "schedule_desc": "~daily",
  "drafts": 7
}
