{
  "bots": 14,
  "reports": {
    "top15": {
      "file": "actionable.html",
      "title": "Most Actionable PRs",
      "count": 45
    },
    "quick-wins": {
      "file": "quick-wins.html",
      "title": "Quick Wins: Ready to Merge",
      "count": 0
    },
    "community": {
      "file": "community.html",
      "title": "Community PRs Awaiting Review",
      "count": 0
    },
    "stale-close": {
      "file": "consider-closing.html",
      "title": "Consider Closing",
      "count": 10
    }
  },
  "drafts": 26,
  "scanned": 85,
  "repo": "dotnet/msbuild",
  "elapsed": 12.0,
  "analyzed": 45,
  "slug": "msbuild",
  "updated": "2026-03-24T02:38:37.1301374Z"
}
