{
  "drafts": 28,
  "bots": 6,
  "repo": "dotnet/aspire",
  "reports": {
    "community": {
      "file": "community.html",
      "count": 6,
      "title": "Community PRs Awaiting Review"
    },
    "quick-wins": {
      "file": "quick-wins.html",
      "count": 6,
      "title": "Quick Wins: Ready to Merge"
    },
    "top15": {
      "file": "actionable.html",
      "count": 70,
      "title": "Most Actionable PRs"
    },
    "stale-close": {
      "file": "consider-closing.html",
      "count": 10,
      "title": "Consider Closing"
    }
  },
  "analyzed": 70,
  "updated": "2026-03-03T20:15:59.3668283Z",
  "slug": "aspire",
  "elapsed": 25.1,
  "scanned": 104
}
