{
  "slug": "sdk",
  "analyzed": 116,
  "reports": {
    "stale-close": {
      "file": "consider-closing.html",
      "count": 45,
      "title": "Consider Closing"
    },
    "community": {
      "file": "community.html",
      "count": 0,
      "title": "Community PRs Awaiting Review"
    },
    "quick-wins": {
      "file": "quick-wins.html",
      "count": 0,
      "title": "Quick Wins: Ready to Merge"
    },
    "top15": {
      "file": "actionable.html",
      "count": 116,
      "title": "Most Actionable PRs"
    }
  },
  "drafts": 87,
  "scanned": 216,
  "bots": 13,
  "repo": "dotnet/sdk",
  "elapsed": 43.2,
  "updated": "2026-03-19T07:08:45.9855938Z"
}
